mcli/cli.py
mcli/config.toml
mcli/app/commands_cmd.py
mcli/app/completion_helpers.py
mcli/app/config_cmd.py
mcli/app/context_cmd.py
mcli/app/create_cmd.py
mcli/app/delete_cmd.py
mcli/app/edit_cmd.py
mcli/app/init_cmd.py
mcli/app/list_cmd.py
mcli/app/main.py
mcli/app/migrate_cmd.py
mcli/app/model_cmd.py
mcli/app/new_cmd.py
mcli/app/remove_cmd.py
mcli/app/rm_cmd.py
mcli/app/search_cmd.py
mcli/app/sync_cmd.py
mcli/app/model/model.py
mcli/app/video/video.py
mcli/chat/chat.py
mcli/chat/command_rag.py
mcli/chat/enhanced_chat.py
mcli/chat/system_controller.py
mcli/chat/system_integration.py
mcli/lib/custom_commands.py
mcli/lib/errors.py
mcli/lib/feature_detection.py
mcli/lib/folder_workflows.py
mcli/lib/ipfs_sync.py
mcli/lib/lib.py
mcli/lib/optional_deps.py
mcli/lib/paths.py
mcli/lib/script_loader.py
mcli/lib/script_sync.py
mcli/lib/script_watcher.py
mcli/lib/types.py
mcli/lib/workspace_registry.py
mcli/lib/api/api.py
mcli/lib/api/daemon_client.py
mcli/lib/api/daemon_client_local.py
mcli/lib/api/daemon_decorator.py
mcli/lib/api/mcli_decorators.py
mcli/lib/auth/auth.py
mcli/lib/auth/aws_manager.py
mcli/lib/auth/azure_manager.py
mcli/lib/auth/credential_manager.py
mcli/lib/auth/gcp_manager.py
mcli/lib/auth/key_manager.py
mcli/lib/auth/mcli_manager.py
mcli/lib/auth/token_manager.py
mcli/lib/auth/token_util.py
mcli/lib/config/config.py
mcli/lib/constants/__init__.py
mcli/lib/constants/commands.py
mcli/lib/constants/defaults.py
mcli/lib/constants/env.py
mcli/lib/constants/messages.py
mcli/lib/constants/paths.py
mcli/lib/constants/scripts.py
mcli/lib/constants/storage.py
mcli/lib/discovery/__init__.py
mcli/lib/discovery/command_discovery.py
mcli/lib/erd/erd.py
mcli/lib/erd/generate_graph.py
mcli/lib/files/files.py
mcli/lib/fs/fs.py
mcli/lib/logger/logger.py
mcli/lib/performance/optimizer.py
mcli/lib/performance/rust_bridge.py
mcli/lib/performance/uvloop_config.py
mcli/lib/pickles/pickles.py
mcli/lib/search/cached_vectorizer.py
mcli/lib/secrets/commands.py
mcli_framework-8.0.6.dist-info/licenses/LICENSE
mcli_framework-8.0.6.dist-info/METADATA
mcli_framework-8.0.6.dist-info/WHEEL
mcli_framework-8.0.6.dist-info/entry_points.txt
mcli_framework-8.0.6.dist-info/top_level.txt
mcli_framework-8.0.6.dist-info/RECORD
