Metadata-Version: 2.4
Name: mcli-framework
Version: 8.0.6
Summary: Portable workflow framework - transform any script into a versioned, schedulable command. Store in ~/.mcli/workflows/, version with lockfile, run as daemon or cron job.
Author-email: Luis Fernandez de la Vara <luis@lefv.io>
Maintainer-email: Luis Fernandez de la Vara <luis@lefv.io>
License: MIT
Project-URL: Homepage, https://github.com/gwicho38/mcli
Project-URL: Repository, https://github.com/gwicho38/mcli
Project-URL: Documentation, https://github.com/gwicho38/mcli#readme
Project-URL: Issues, https://github.com/gwicho38/mcli/issues
Project-URL: Changelog, https://github.com/gwicho38/mcli/releases
Project-URL: Source, https://github.com/gwicho38/mcli
Keywords: cli,command-line,framework,chat,assistant,rust,performance,visual,tui,terminal,ai,openai,anthropic,productivity
Classifier: Development Status :: 4 - Beta
Classifier: Environment :: Console
Classifier: Intended Audience :: Developers
Classifier: Intended Audience :: System Administrators
Classifier: License :: OSI Approved :: MIT License
Classifier: Operating System :: OS Independent
Classifier: Operating System :: POSIX :: Linux
Classifier: Operating System :: MacOS
Classifier: Operating System :: Microsoft :: Windows
Classifier: Programming Language :: Python :: 3
Classifier: Programming Language :: Python :: 3.10
Classifier: Programming Language :: Python :: 3.11
Classifier: Programming Language :: Python :: 3.12
Classifier: Programming Language :: Rust
Classifier: Topic :: Software Development :: Libraries :: Python Modules
Classifier: Topic :: System :: Shells
Classifier: Topic :: System :: Systems Administration
Classifier: Topic :: Terminals
Classifier: Topic :: Utilities
Classifier: Topic :: Scientific/Engineering :: Artificial Intelligence
Classifier: Typing :: Typed
Requires-Python: >=3.10
License-File: LICENSE
Requires-Dist: click<9.0.0,>=8.1.7
Requires-Dist: rich>=14.0.0
Requires-Dist: requests<3.0.0,>=2.31.0
Requires-Dist: tomli>=2.2.1
Requires-Dist: python-dotenv>=1.1.1
Requires-Dist: watchdog<4.0.0,>=3.0.0
Requires-Dist: tqdm<5.0.0,>=4.66.1
Requires-Dist: humanize<5.0.0,>=4.9.0
Requires-Dist: psutil<6.0.0,>=5.9.0
Requires-Dist: inquirerpy<0.4.0,>=0.3.4
Requires-Dist: gitpython<4.0.0,>=3.1.40
Requires-Dist: prompt-toolkit<4.0.0,>=3.0.0
Requires-Dist: aiohttp>=3.9.0
Requires-Dist: httpx>=0.28.1
Requires-Dist: websockets>=12.0
Requires-Dist: beautifulsoup4>=4.13.5
Requires-Dist: fuzzywuzzy>=0.18.0
Requires-Dist: openai<2.0.0,>=1.3.0
Requires-Dist: anthropic>=0.60.0
Requires-Dist: ollama>=0.5.3
Requires-Dist: ipython<9.0.0,>=8.12.0
Requires-Dist: fastapi>=0.110.0
Requires-Dist: uvicorn>=0.27.0
Requires-Dist: uvloop>=0.19.0
Requires-Dist: aiosqlite>=0.20.0
Requires-Dist: redis>=5.0.0
Requires-Dist: aiohttp-sse-client>=0.2.1
Requires-Dist: aiomqtt>=2.0.0
Requires-Dist: opencv-python>=4.11.0.86
Requires-Dist: pillow>=11.2.1
Requires-Dist: numpy<2.0.0,>=1.24.0
Requires-Dist: scikit-image>=0.24.0
Requires-Dist: scipy>=1.10.0
Requires-Dist: pypdf2>=3.0.1
Requires-Dist: pymupdf>=1.26.3
Requires-Dist: pandas>=2.3.1
Requires-Dist: openpyxl>=3.1.5
Requires-Dist: matplotlib>=3.9.4
Requires-Dist: pydot>=4.0.1
Requires-Dist: graphviz>=0.21
Requires-Dist: seaborn>=0.13.0
Requires-Dist: plotly>=5.17.0
Requires-Dist: supabase>=2.8.1
Requires-Dist: sqlalchemy>=2.0.0
Requires-Dist: alembic>=1.12.0
Requires-Dist: psycopg2-binary>=2.9.7
Requires-Dist: asyncpg>=0.29.0
Requires-Dist: torch>=2.0.0
Requires-Dist: torchvision>=0.15.0
Requires-Dist: pytorch-lightning>=2.0.0
Requires-Dist: scikit-learn<2.0.0,>=1.3.0
Requires-Dist: mlflow>=2.9.0
Requires-Dist: dvc>=3.0.0
Requires-Dist: polars>=0.19.0
Requires-Dist: pyarrow>=14.0.0
Requires-Dist: yfinance>=0.2.18
Requires-Dist: alpha-vantage>=2.3.1
Requires-Dist: alpaca-py==0.43.2
Requires-Dist: cvxpy>=1.4.0
Requires-Dist: python-jose[cryptography]>=3.3.0
Requires-Dist: passlib[bcrypt]>=1.7.4
Requires-Dist: pydantic-settings>=2.1.0
Requires-Dist: dynaconf>=3.2.0
Requires-Dist: pandera>=0.17.0
Requires-Dist: pendulum>=2.1.2
Requires-Dist: optuna>=3.4.0
Requires-Dist: PyPortfolioOpt>=1.5.5
Requires-Dist: jupyter>=1.0.0
Requires-Dist: jupyterlab>=4.0.0
Requires-Dist: ipykernel>=6.27.0
Requires-Dist: prometheus-client>=0.19.0
Requires-Dist: structlog>=23.2.0
Requires-Dist: gunicorn>=21.2.0
Requires-Dist: newrelic>=9.2.0
Requires-Dist: datadog>=0.49.0
Requires-Dist: orjson>=3.9.0
Requires-Dist: kafka-python>=2.0.2
Requires-Dist: streamlit>=1.50.0
Requires-Dist: altair<5.0.0,>=4.2.1
Requires-Dist: streamlit-autorefresh>=1.0.1
Requires-Dist: typer>=0.9.0
Requires-Dist: flask<3.0.0,>=2.3.0
Provides-Extra: gpu
Requires-Dist: cupy-cuda12x>=12.3.0; extra == "gpu"
Requires-Dist: nvidia-ml-py>=12.535.0; extra == "gpu"
Provides-Extra: ml-plugin
Requires-Dist: torch>=2.0.0; extra == "ml-plugin"
Requires-Dist: torchvision>=0.15.0; extra == "ml-plugin"
Requires-Dist: pytorch-lightning>=2.0.0; extra == "ml-plugin"
Requires-Dist: scikit-learn<2.0.0,>=1.3.0; extra == "ml-plugin"
Requires-Dist: mlflow>=2.9.0; extra == "ml-plugin"
Requires-Dist: dvc>=3.0.0; extra == "ml-plugin"
Requires-Dist: optuna>=3.4.0; extra == "ml-plugin"
Requires-Dist: streamlit>=1.50.0; extra == "ml-plugin"
Requires-Dist: altair<5.0.0,>=4.2.1; extra == "ml-plugin"
Requires-Dist: streamlit-autorefresh>=1.0.1; extra == "ml-plugin"
Requires-Dist: pandas>=2.3.1; extra == "ml-plugin"
Requires-Dist: numpy<2.0.0,>=1.24.0; extra == "ml-plugin"
Requires-Dist: polars>=0.19.0; extra == "ml-plugin"
Requires-Dist: pyarrow>=14.0.0; extra == "ml-plugin"
Provides-Extra: video-plugin
Requires-Dist: opencv-python>=4.11.0.86; extra == "video-plugin"
Requires-Dist: pillow>=11.2.1; extra == "video-plugin"
Requires-Dist: numpy<2.0.0,>=1.24.0; extra == "video-plugin"
Requires-Dist: scikit-image>=0.24.0; extra == "video-plugin"
Requires-Dist: scipy>=1.10.0; extra == "video-plugin"
Provides-Extra: trading-plugin
Requires-Dist: yfinance>=0.2.18; extra == "trading-plugin"
Requires-Dist: alpha-vantage>=2.3.1; extra == "trading-plugin"
Requires-Dist: alpaca-py==0.43.2; extra == "trading-plugin"
Requires-Dist: cvxpy>=1.4.0; extra == "trading-plugin"
Requires-Dist: PyPortfolioOpt>=1.5.5; extra == "trading-plugin"
Requires-Dist: pandas>=2.3.1; extra == "trading-plugin"
Requires-Dist: numpy<2.0.0,>=1.24.0; extra == "trading-plugin"
Provides-Extra: chat
Provides-Extra: async-extras
Provides-Extra: video
Provides-Extra: documents
Provides-Extra: viz
Provides-Extra: database
Provides-Extra: ml
Provides-Extra: monitoring
Provides-Extra: streaming
Provides-Extra: dashboard
Provides-Extra: web
Provides-Extra: dev
Requires-Dist: pytest>=8.4.1; extra == "dev"
Requires-Dist: pytest-cov<5.0.0,>=4.1.0; extra == "dev"
Requires-Dist: pytest-mock>=3.14.1; extra == "dev"
Requires-Dist: pytest-asyncio>=1.1.0; extra == "dev"
Requires-Dist: pytest-benchmark>=4.0.0; extra == "dev"
Requires-Dist: pytest-timeout>=2.2.0; extra == "dev"
Requires-Dist: pytest-xdist>=3.5.0; extra == "dev"
Requires-Dist: hypothesis>=6.92.0; extra == "dev"
Requires-Dist: faker>=22.0.0; extra == "dev"
Requires-Dist: responses>=0.24.0; extra == "dev"
Requires-Dist: freezegun>=1.4.0; extra == "dev"
Requires-Dist: pytest-html>=4.1.0; extra == "dev"
Requires-Dist: pytest-json-report>=1.5.0; extra == "dev"
Requires-Dist: black>=23.0.0; extra == "dev"
Requires-Dist: isort<6.0.0,>=5.12.0; extra == "dev"
Requires-Dist: mypy<2.0.0,>=1.7.1; extra == "dev"
Requires-Dist: ruff>=0.1.0; extra == "dev"
Requires-Dist: pre-commit>=4.5.1; extra == "dev"
Requires-Dist: build>=1.2.2.post1; extra == "dev"
Requires-Dist: maturin>=1.9.3; extra == "dev"
Requires-Dist: twine>=4.0.0; extra == "dev"
Provides-Extra: all
Dynamic: license-file
